chemxls/__init__.py
chemxls/__main__.py
chemxls-0.0.1.post5.dist-info/LICENSE.txt
chemxls-0.0.1.post5.dist-info/METADATA
chemxls-0.0.1.post5.dist-info/WHEEL
chemxls-0.0.1.post5.dist-info/top_level.txt
chemxls-0.0.1.post5.dist-info/RECORD
