Metadata-Version: 2.1
Name: chemxls
Version: 0.0.1.post5
Summary: chemxls is a python & tk application for creating xls files (spreadsheets) bases on computational chemistry inputs and outputs.
Home-page: https://github.com/ricalmang/chemxls
Author: Ricardo Almir Angnes
Author-email: ricardo_almir@hotmail.com
License: MIT
Keywords: chemistry
Platform: UNKNOWN
Classifier: Programming Language :: Python :: 3
Classifier: License :: OSI Approved :: MIT License
Classifier: Operating System :: OS Independent
Requires-Python: >=3.8
Requires-Dist: xlwt
Requires-Dist: numpy
